LICENSE
MANIFEST.in
README.md
dev_requirements.txt
requirements.txt
setup.py
runfile/__init__.py
runfile/cache.py
runfile/cli.py
runfile/code_block.py
runfile/exceptions.py
runfile/target.py
runfile/util.py
runfile/vars.py
runfile.egg-info/PKG-INFO
runfile.egg-info/SOURCES.txt
runfile.egg-info/dependency_links.txt
runfile.egg-info/entry_points.txt
runfile.egg-info/requires.txt
runfile.egg-info/top_level.txt
runfile/resources/completion.bash