Metadata-Version: 2.1
Name: runfile
Version: 1.0.7
Summary: A generic task-based automation format.
Home-page: https://github.com/awkspace/runfile
Author: awk
Author-email: awk@awk.space
License: MIT
Platform: UNKNOWN
Provides-Extra: dev
License-File: LICENSE
